[
  {
    "id": 909462,
    "startDate": "Wed Feb 24 17:14:00 UTC 2021",
    "etrDate": "Thu Feb 25 03:17:00 UTC 2021",
    "type": "OUTAGE",
    "title": "Outage",
    "numPeople": 60,
    "mapPinUrl": "",
    "status": "",
    "cause": "Planned Work",
    "identifier": "123211",
    "latitude": 47.50580651977888,
    "longitude": -122.38500541610938,
    "polygons": [
      {
        "points": [
          {
            "latitude": 47.5046753,
            "longitude": -122.3857785
          },
          {
            "latitude": 47.5046932,
            "longitude": -122.3858833
          },
          {
            "latitude": 47.5048327,
            "longitude": -122.3862779
          },
          {
            "latitude": 47.5048568,
            "longitude": -122.3863303
          },
          {
            "latitude": 47.5049719,
            "longitude": -122.3864454
          },
          {
            "latitude": 47.5050172,
            "longitude": -122.3864575
          },
          {
            "latitude": 47.5050182,
            "longitude": -122.3864614
          },
          {
            "latitude": 47.5050611,
            "longitude": -122.3865193
          },
          {
            "latitude": 47.5054241,
            "longitude": -122.3869064
          },
          {
            "latitude": 47.5054963,
            "longitude": -122.3869637
          },
          {
            "latitude": 47.5055217,
            "longitude": -122.3869705
          },
          {
            "latitude": 47.5055995,
            "longitude": -122.3870773
          },
          {
            "latitude": 47.5056355,
            "longitude": -122.3871186
          },
          {
            "latitude": 47.5057516,
            "longitude": -122.3872305
          },
          {
            "latitude": 47.5058051,
            "longitude": -122.3872719
          },
          {
            "latitude": 47.5059397,
            "longitude": -122.3873546
          },
          {
            "latitude": 47.5059452,
            "longitude": -122.3873579
          },
          {
            "latitude": 47.5059519,
            "longitude": -122.3873831
          },
          {
            "latitude": 47.5060179,
            "longitude": -122.3874631
          },
          {
            "latitude": 47.5064237,
            "longitude": -122.3878161
          },
          {
            "latitude": 47.5064728,
            "longitude": -122.3878511
          },
          {
            "latitude": 47.50663,
            "longitude": -122.3878933
          },
          {
            "latitude": 47.5067872,
            "longitude": -122.3878511
          },
          {
            "latitude": 47.5069023,
            "longitude": -122.3877361
          },
          {
            "latitude": 47.5069444,
            "longitude": -122.3875789
          },
          {
            "latitude": 47.5069023,
            "longitude": -122.3874217
          },
          {
            "latitude": 47.5068662,
            "longitude": -122.3873713
          },
          {
            "latitude": 47.5067616,
            "longitude": -122.3872523
          },
          {
            "latitude": 47.5067249,
            "longitude": -122.3872168
          },
          {
            "latitude": 47.506565,
            "longitude": -122.3870855
          },
          {
            "latitude": 47.5065501,
            "longitude": -122.387074
          },
          {
            "latitude": 47.506462,
            "longitude": -122.38701
          },
          {
            "latitude": 47.5066359,
            "longitude": -122.3864938
          },
          {
            "latitude": 47.5066523,
            "longitude": -122.3863934
          },
          {
            "latitude": 47.5066102,
            "longitude": -122.3862362
          },
          {
            "latitude": 47.5065486,
            "longitude": -122.38616
          },
          {
            "latitude": 47.5064233,
            "longitude": -122.3860469
          },
          {
            "latitude": 47.5064392,
            "longitude": -122.3860426
          },
          {
            "latitude": 47.5065543,
            "longitude": -122.3859275
          },
          {
            "latitude": 47.5065964,
            "longitude": -122.3857703
          },
          {
            "latitude": 47.5065961,
            "longitude": -122.3857552
          },
          {
            "latitude": 47.5065575,
            "longitude": -122.3849533
          },
          {
            "latitude": 47.5065219,
            "longitude": -122.3848223
          },
          {
            "latitude": 47.5064564,
            "longitude": -122.3846976
          },
          {
            "latitude": 47.5064503,
            "longitude": -122.3846865
          },
          {
            "latitude": 47.5063352,
            "longitude": -122.3845714
          },
          {
            "latitude": 47.5063191,
            "longitude": -122.3845671
          },
          {
            "latitude": 47.5063157,
            "longitude": -122.3845626
          },
          {
            "latitude": 47.5064364,
            "longitude": -122.3845302
          },
          {
            "latitude": 47.5065515,
            "longitude": -122.3844151
          },
          {
            "latitude": 47.5065936,
            "longitude": -122.3842579
          },
          {
            "latitude": 47.5065936,
            "longitude": -122.3842556
          },
          {
            "latitude": 47.5065881,
            "longitude": -122.3835312
          },
          {
            "latitude": 47.506546,
            "longitude": -122.3833764
          },
          {
            "latitude": 47.5064719,
            "longitude": -122.3833022
          },
          {
            "latitude": 47.5064979,
            "longitude": -122.3832762
          },
          {
            "latitude": 47.50654,
            "longitude": -122.383119
          },
          {
            "latitude": 47.5065368,
            "longitude": -122.3830744
          },
          {
            "latitude": 47.5064639,
            "longitude": -122.3825658
          },
          {
            "latitude": 47.506425,
            "longitude": -122.3824532
          },
          {
            "latitude": 47.5063099,
            "longitude": -122.3823381
          },
          {
            "latitude": 47.506182,
            "longitude": -122.3822974
          },
          {
            "latitude": 47.5056732,
            "longitude": -122.3822497
          },
          {
            "latitude": 47.5056439,
            "longitude": -122.3822483
          },
          {
            "latitude": 47.5054867,
            "longitude": -122.3822904
          },
          {
            "latitude": 47.5053716,
            "longitude": -122.3824055
          },
          {
            "latitude": 47.5053295,
            "longitude": -122.3825575
          },
          {
            "latitude": 47.5053185,
            "longitude": -122.3832241
          },
          {
            "latitude": 47.5053184,
            "longitude": -122.3832293
          },
          {
            "latitude": 47.5053335,
            "longitude": -122.3832856
          },
          {
            "latitude": 47.5053115,
            "longitude": -122.3833067
          },
          {
            "latitude": 47.5050802,
            "longitude": -122.3836684
          },
          {
            "latitude": 47.5050777,
            "longitude": -122.3836724
          },
          {
            "latitude": 47.5049638,
            "longitude": -122.3838566
          },
          {
            "latitude": 47.5049589,
            "longitude": -122.3838648
          },
          {
            "latitude": 47.5049167,
            "longitude": -122.384022
          },
          {
            "latitude": 47.5049283,
            "longitude": -122.3840651
          },
          {
            "latitude": 47.5048928,
            "longitude": -122.3841006
          },
          {
            "latitude": 47.504856,
            "longitude": -122.3842003
          },
          {
            "latitude": 47.5048053,
            "longitude": -122.3844732
          },
          {
            "latitude": 47.5048009,
            "longitude": -122.384506
          },
          {
            "latitude": 47.5047702,
            "longitude": -122.3848963
          },
          {
            "latitude": 47.5047693,
            "longitude": -122.3849209
          },
          {
            "latitude": 47.5048114,
            "longitude": -122.3850781
          },
          {
            "latitude": 47.5048158,
            "longitude": -122.3850825
          },
          {
            "latitude": 47.504802,
            "longitude": -122.3850962
          },
          {
            "latitude": 47.5047658,
            "longitude": -122.3851929
          },
          {
            "latitude": 47.5047043,
            "longitude": -122.3855065
          },
          {
            "latitude": 47.5047003,
            "longitude": -122.3855328
          },
          {
            "latitude": 47.5046771,
            "longitude": -122.3857443
          }
        ]
      }
    ],
    "publicVisibility": true,
    "enabled": false,
    "manual": false,
    "images": [],
    "rules": [],
    "actions": [],
    "city": "South Seattle",
    "state": "WA",
    "affectedMunicipalities": [],
    "affectedCounties": [],
    "affectedDistricts": []
  },
  {
    "id": 909775,
    "startDate": "Wed Feb 24 19:36:00 UTC 2021",
    "etrDate": "Thu Feb 25 04:00:00 UTC 2021",
    "type": "OUTAGE",
    "title": "Outage",
    "numPeople": 1685,
    "mapPinUrl": "",
    "status": "",
    "cause": "Investigating",
    "identifier": "123232",
    "latitude": 47.60555508359388,
    "longitude": -122.29070506808485,
    "polygons": [
      {
        "points": [
          {
            "latitude": 47.6018107,
            "longitude": -122.2846051
          },
          {
            "latitude": 47.6017865,
            "longitude": -122.284641
          },
          {
            "latitude": 47.6017749,
            "longitude": -122.2846596
          },
          {
            "latitude": 47.6017327,
            "longitude": -122.2848168
          },
          {
            "latitude": 47.6017749,
            "longitude": -122.284974
          },
          {
            "latitude": 47.6017865,
            "longitude": -122.2849925
          },
          {
            "latitude": 47.6018107,
            "longitude": -122.2850284
          },
          {
            "latitude": 47.6019141,
            "longitude": -122.285125
          },
          {
            "latitude": 47.6020713,
            "longitude": -122.2851671
          },
          {
            "latitude": 47.6022285,
            "longitude": -122.285125
          },
          {
            "latitude": 47.602332,
            "longitude": -122.2850284
          },
          {
            "latitude": 47.6023562,
            "longitude": -122.2849925
          },
          {
            "latitude": 47.6023678,
            "longitude": -122.284974
          },
          {
            "latitude": 47.60241,
            "longitude": -122.2848168
          },
          {
            "latitude": 47.6023678,
            "longitude": -122.2846596
          },
          {
            "latitude": 47.6023562,
            "longitude": -122.284641
          },
          {
            "latitude": 47.602332,
            "longitude": -122.2846051
          },
          {
            "latitude": 47.6022285,
            "longitude": -122.2845086
          },
          {
            "latitude": 47.6020713,
            "longitude": -122.2844665
          },
          {
            "latitude": 47.6019141,
            "longitude": -122.2845086
          }
        ]
      },
      {
        "points": [
          {
            "latitude": 47.6027072,
            "longitude": -122.2839544
          },
          {
            "latitude": 47.602683,
            "longitude": -122.2839903
          },
          {
            "latitude": 47.6026714,
            "longitude": -122.2840088
          },
          {
            "latitude": 47.6026293,
            "longitude": -122.284166
          },
          {
            "latitude": 47.6026714,
            "longitude": -122.2843232
          },
          {
            "latitude": 47.602683,
            "longitude": -122.2843418
          },
          {
            "latitude": 47.6027072,
            "longitude": -122.2843777
          },
          {
            "latitude": 47.6028107,
            "longitude": -122.2844742
          },
          {
            "latitude": 47.6029679,
            "longitude": -122.2845163
          },
          {
            "latitude": 47.6031251,
            "longitude": -122.2844742
          },
          {
            "latitude": 47.6032286,
            "longitude": -122.2843777
          },
          {
            "latitude": 47.6032528,
            "longitude": -122.2843418
          },
          {
            "latitude": 47.6032644,
            "longitude": -122.2843232
          },
          {
            "latitude": 47.6033065,
            "longitude": -122.284166
          },
          {
            "latitude": 47.6032644,
            "longitude": -122.2840088
          },
          {
            "latitude": 47.6032528,
            "longitude": -122.2839903
          },
          {
            "latitude": 47.6032286,
            "longitude": -122.2839544
          },
          {
            "latitude": 47.6031251,
            "longitude": -122.2838578
          },
          {
            "latitude": 47.6029679,
            "longitude": -122.2838157
          },
          {
            "latitude": 47.6028107,
            "longitude": -122.2838578
          }
        ]
      },
      {
        "points": [
          {
            "latitude": 47.598435,
            "longitude": -122.2953254
          },
          {
            "latitude": 47.5984771,
            "longitude": -122.2954826
          },
          {
            "latitude": 47.5984887,
            "longitude": -122.2955012
          },
          {
            "latitude": 47.5985129,
            "longitude": -122.2955371
          },
          {
            "latitude": 47.5986164,
            "longitude": -122.2956336
          },
          {
            "latitude": 47.5987736,
            "longitude": -122.2956757
          },
          {
            "latitude": 47.5989308,
            "longitude": -122.2956336
          },
          {
            "latitude": 47.599033,
            "longitude": -122.2955383
          },
          {
            "latitude": 47.5993656,
            "longitude": -122.2956381
          },
          {
            "latitude": 47.5993889,
            "longitude": -122.2956441
          },
          {
            "latitude": 47.5996197,
            "longitude": -122.2956944
          },
          {
            "latitude": 47.5995994,
            "longitude": -122.2957103
          },
          {
            "latitude": 47.5991098,
            "longitude": -122.2962174
          },
          {
            "latitude": 47.5990637,
            "longitude": -122.2962786
          },
          {
            "latitude": 47.5990216,
            "longitude": -122.2964358
          },
          {
            "latitude": 47.5990637,
            "longitude": -122.296593
          },
          {
            "latitude": 47.5991788,
            "longitude": -122.2967081
          },
          {
            "latitude": 47.5992808,
            "longitude": -122.2967453
          },
          {
            "latitude": 47.5996247,
            "longitude": -122.2968067
          },
          {
            "latitude": 47.5996799,
            "longitude": -122.2968115
          },
          {
            "latitude": 47.5996918,
            "longitude": -122.2968113
          },
          {
            "latitude": 47.5998158,
            "longitude": -122.2968066
          },
          {
            "latitude": 47.5998196,
            "longitude": -122.2969226
          },
          {
            "latitude": 47.5998615,
            "longitude": -122.2970696
          },
          {
            "latitude": 47.5999766,
            "longitude": -122.2971847
          },
          {
            "latitude": 47.6001338,
            "longitude": -122.2972268
          },
          {
            "latitude": 47.600291,
            "longitude": -122.2971847
          },
          {
            "latitude": 47.6004061,
            "longitude": -122.2970696
          },
          {
            "latitude": 47.6004156,
            "longitude": -122.2970519
          },
          {
            "latitude": 47.6004579,
            "longitude": -122.2969664
          },
          {
            "latitude": 47.6005284,
            "longitude": -122.2969578
          },
          {
            "latitude": 47.6007067,
            "longitude": -122.296914
          },
          {
            "latitude": 47.600722,
            "longitude": -122.2969099
          },
          {
            "latitude": 47.6011543,
            "longitude": -122.2967804
          },
          {
            "latitude": 47.6012213,
            "longitude": -122.2967515
          },
          {
            "latitude": 47.6013364,
            "longitude": -122.2966364
          },
          {
            "latitude": 47.6013659,
            "longitude": -122.2965266
          },
          {
            "latitude": 47.6014745,
            "longitude": -122.2965557
          },
          {
            "latitude": 47.6016317,
            "longitude": -122.2965135
          },
          {
            "latitude": 47.6016847,
            "longitude": -122.2964641
          },
          {
            "latitude": 47.6017025,
            "longitude": -122.2965304
          },
          {
            "latitude": 47.6017141,
            "longitude": -122.296549
          },
          {
            "latitude": 47.6017383,
            "longitude": -122.2965849
          },
          {
            "latitude": 47.6018418,
            "longitude": -122.2966814
          },
          {
            "latitude": 47.601999,
            "longitude": -122.2967235
          },
          {
            "latitude": 47.6021562,
            "longitude": -122.2966814
          },
          {
            "latitude": 47.6022409,
            "longitude": -122.2966024
          },
          {
            "latitude": 47.6023064,
            "longitude": -122.2966209
          },
          {
            "latitude": 47.6027176,
            "longitude": -122.2966323
          },
          {
            "latitude": 47.6027263,
            "longitude": -122.2966324
          },
          {
            "latitude": 47.6028604,
            "longitude": -122.2965965
          },
          {
            "latitude": 47.6033588,
            "longitude": -122.2966552
          },
          {
            "latitude": 47.6033955,
            "longitude": -122.2966574
          },
          {
            "latitude": 47.6034375,
            "longitude": -122.2966461
          },
          {
            "latitude": 47.6034395,
            "longitude": -122.2966537
          },
          {
            "latitude": 47.6035546,
            "longitude": -122.2967687
          },
          {
            "latitude": 47.6036935,
            "longitude": -122.2968103
          },
          {
            "latitude": 47.6040662,
            "longitude": -122.296832
          },
          {
            "latitude": 47.6040844,
            "longitude": -122.2968326
          },
          {
            "latitude": 47.6042013,
            "longitude": -122.29681
          },
          {
            "latitude": 47.6058887,
            "longitude": -122.2961345
          },
          {
            "latitude": 47.605929,
            "longitude": -122.2961149
          },
          {
            "latitude": 47.6060163,
            "longitude": -122.2960276
          },
          {
            "latitude": 47.6060203,
            "longitude": -122.2964437
          },
          {
            "latitude": 47.6060624,
            "longitude": -122.2965978
          },
          {
            "latitude": 47.6061775,
            "longitude": -122.2967129
          },
          {
            "latitude": 47.6063347,
            "longitude": -122.296755
          },
          {
            "latitude": 47.6064919,
            "longitude": -122.2967129
          },
          {
            "latitude": 47.6065258,
            "longitude": -122.2966903
          },
          {
            "latitude": 47.606862,
            "longitude": -122.2964331
          },
          {
            "latitude": 47.6068742,
            "longitude": -122.2964364
          },
          {
            "latitude": 47.6072821,
            "longitude": -122.2964415
          },
          {
            "latitude": 47.607286,
            "longitude": -122.2964415
          },
          {
            "latitude": 47.6074432,
            "longitude": -122.2963994
          },
          {
            "latitude": 47.6075218,
            "longitude": -122.2963209
          },
          {
            "latitude": 47.6075965,
            "longitude": -122.2963956
          },
          {
            "latitude": 47.6077537,
            "longitude": -122.2964377
          },
          {
            "latitude": 47.6079109,
            "longitude": -122.2963956
          },
          {
            "latitude": 47.6079275,
            "longitude": -122.2963853
          },
          {
            "latitude": 47.6079918,
            "longitude": -122.2963427
          },
          {
            "latitude": 47.6078988,
            "longitude": -122.296479
          },
          {
            "latitude": 47.6078862,
            "longitude": -122.296499
          },
          {
            "latitude": 47.6078441,
            "longitude": -122.2966562
          },
          {
            "latitude": 47.6078862,
            "longitude": -122.2968134
          },
          {
            "latitude": 47.6080013,
            "longitude": -122.2969285
          },
          {
            "latitude": 47.6080265,
            "longitude": -122.2969416
          },
          {
            "latitude": 47.6082463,
            "longitude": -122.2970432
          },
          {
            "latitude": 47.6082588,
            "longitude": -122.2970487
          },
          {
            "latitude": 47.6083531,
            "longitude": -122.2970874
          },
          {
            "latitude": 47.6084725,
            "longitude": -122.297111
          },
          {
            "latitude": 47.6086297,
            "longitude": -122.2970688
          },
          {
            "latitude": 47.6086921,
            "longitude": -122.2970216
          },
          {
            "latitude": 47.6088979,
            "longitude": -122.2968208
          },
          {
            "latitude": 47.609116,
            "longitude": -122.2968995
          },
          {
            "latitude": 47.6092227,
            "longitude": -122.2969181
          },
          {
            "latitude": 47.6092328,
            "longitude": -122.2969179
          },
          {
            "latitude": 47.6095781,
            "longitude": -122.2969068
          },
          {
            "latitude": 47.6096343,
            "longitude": -122.2968999
          },
          {
            "latitude": 47.6096507,
            "longitude": -122.2968964
          },
          {
            "latitude": 47.6097235,
            "longitude": -122.2969692
          },
          {
            "latitude": 47.6097855,
            "longitude": -122.2969966
          },
          {
            "latitude": 47.6100551,
            "longitude": -122.2970823
          },
          {
            "latitude": 47.6101504,
            "longitude": -122.2970971
          },
          {
            "latitude": 47.6103076,
            "longitude": -122.297055
          },
          {
            "latitude": 47.610417,
            "longitude": -122.2969493
          },
          {
            "latitude": 47.6104789,
            "longitude": -122.2968502
          },
          {
            "latitude": 47.6105026,
            "longitude": -122.2968539
          },
          {
            "latitude": 47.610652,
            "longitude": -122.2968608
          },
          {
            "latitude": 47.6106664,
            "longitude": -122.2968611
          },
          {
            "latitude": 47.6107888,
            "longitude": -122.2968283
          },
          {
            "latitude": 47.6108042,
            "longitude": -122.2968334
          },
          {
            "latitude": 47.6109052,
            "longitude": -122.2968456
          },
          {
            "latitude": 47.6109289,
            "longitude": -122.2968475
          },
          {
            "latitude": 47.6113907,
            "longitude": -122.296868
          },
          {
            "latitude": 47.6114046,
            "longitude": -122.2968683
          },
          {
            "latitude": 47.6115618,
            "longitude": -122.2968262
          },
          {
            "latitude": 47.6116769,
            "longitude": -122.2967111
          },
          {
            "latitude": 47.6117111,
            "longitude": -122.2966239
          },
          {
            "latitude": 47.6118366,
            "longitude": -122.2960744
          },
          {
            "latitude": 47.6118444,
            "longitude": -122.2960044
          },
          {
            "latitude": 47.6118023,
            "longitude": -122.2958472
          },
          {
            "latitude": 47.6116872,
            "longitude": -122.2957322
          },
          {
            "latitude": 47.6116486,
            "longitude": -122.2957132
          },
          {
            "latitude": 47.61144,
            "longitude": -122.2956283
          },
          {
            "latitude": 47.6113215,
            "longitude": -122.2956051
          },
          {
            "latitude": 47.6113129,
            "longitude": -122.2956053
          },
          {
            "latitude": 47.6111208,
            "longitude": -122.2956105
          },
          {
            "latitude": 47.6110732,
            "longitude": -122.2956239
          },
          {
            "latitude": 47.6110345,
            "longitude": -122.2956135
          },
          {
            "latitude": 47.61102,
            "longitude": -122.2956139
          },
          {
            "latitude": 47.610693,
            "longitude": -122.2956289
          },
          {
            "latitude": 47.6106861,
            "longitude": -122.2955556
          },
          {
            "latitude": 47.6107696,
            "longitude": -122.2955526
          },
          {
            "latitude": 47.6109155,
            "longitude": -122.2955107
          },
          {
            "latitude": 47.6110306,
            "longitude": -122.2953956
          },
          {
            "latitude": 47.6110727,
            "longitude": -122.2952384
          },
          {
            "latitude": 47.6110726,
            "longitude": -122.2952324
          },
          {
            "latitude": 47.6110607,
            "longitude": -122.2946103
          },
          {
            "latitude": 47.6110186,
            "longitude": -122.2944591
          },
          {
            "latitude": 47.6109036,
            "longitude": -122.294344
          },
          {
            "latitude": 47.6107464,
            "longitude": -122.2943019
          },
          {
            "latitude": 47.6107449,
            "longitude": -122.2943019
          },
          {
            "latitude": 47.6107358,
            "longitude": -122.2943019
          },
          {
            "latitude": 47.6108117,
            "longitude": -122.2942261
          },
          {
            "latitude": 47.6108538,
            "longitude": -122.2940689
          },
          {
            "latitude": 47.6108314,
            "longitude": -122.2939524
          },
          {
            "latitude": 47.6105919,
            "longitude": -122.2933519
          },
          {
            "latitude": 47.6105722,
            "longitude": -122.2933112
          },
          {
            "latitude": 47.6104571,
            "longitude": -122.2931961
          },
          {
            "latitude": 47.6104405,
            "longitude": -122.2931917
          },
          {
            "latitude": 47.6104713,
            "longitude": -122.2931725
          },
          {
            "latitude": 47.6105775,
            "longitude": -122.2930627
          },
          {
            "latitude": 47.6106197,
            "longitude": -122.2929055
          },
          {
            "latitude": 47.6106182,
            "longitude": -122.292875
          },
          {
            "latitude": 47.6105916,
            "longitude": -122.2926028
          },
          {
            "latitude": 47.6106762,
            "longitude": -122.2925801
          },
          {
            "latitude": 47.6107913,
            "longitude": -122.292465
          },
          {
            "latitude": 47.6108334,
            "longitude": -122.2923078
          },
          {
            "latitude": 47.6108003,
            "longitude": -122.2921674
          },
          {
            "latitude": 47.6105205,
            "longitude": -122.2916067
          },
          {
            "latitude": 47.6105114,
            "longitude": -122.2915899
          },
          {
            "latitude": 47.6104063,
            "longitude": -122.2914847
          },
          {
            "latitude": 47.6104104,
            "longitude": -122.2914836
          },
          {
            "latitude": 47.6105139,
            "longitude": -122.2913871
          },
          {
            "latitude": 47.6105381,
            "longitude": -122.2913512
          },
          {
            "latitude": 47.6105497,
            "longitude": -122.2913326
          },
          {
            "latitude": 47.6105918,
            "longitude": -122.2911754
          },
          {
            "latitude": 47.6105497,
            "longitude": -122.2910182
          },
          {
            "latitude": 47.6105381,
            "longitude": -122.2909997
          },
          {
            "latitude": 47.6105139,
            "longitude": -122.2909638
          },
          {
            "latitude": 47.6104104,
            "longitude": -122.2908673
          },
          {
            "latitude": 47.6104054,
            "longitude": -122.2908659
          },
          {
            "latitude": 47.610422,
            "longitude": -122.290826
          },
          {
            "latitude": 47.6105714,
            "longitude": -122.2902743
          },
          {
            "latitude": 47.6105824,
            "longitude": -122.2901921
          },
          {
            "latitude": 47.6105402,
            "longitude": -122.2900349
          },
          {
            "latitude": 47.6104476,
            "longitude": -122.2899422
          },
          {
            "latitude": 47.6105262,
            "longitude": -122.2898636
          },
          {
            "latitude": 47.6105683,
            "longitude": -122.2897064
          },
          {
            "latitude": 47.6105611,
            "longitude": -122.2896395
          },
          {
            "latitude": 47.6105049,
            "longitude": -122.2893814
          },
          {
            "latitude": 47.6105549,
            "longitude": -122.2893314
          },
          {
            "latitude": 47.6105621,
            "longitude": -122.2893182
          },
          {
            "latitude": 47.6108604,
            "longitude": -122.2887393
          },
          {
            "latitude": 47.6108953,
            "longitude": -122.2885953
          },
          {
            "latitude": 47.6108532,
            "longitude": -122.2884381
          },
          {
            "latitude": 47.6107381,
            "longitude": -122.288323
          },
          {
            "latitude": 47.6105809,
            "longitude": -122.2882809
          },
          {
            "latitude": 47.6105376,
            "longitude": -122.2882839
          },
          {
            "latitude": 47.6101929,
            "longitude": -122.2883319
          },
          {
            "latitude": 47.610079,
            "longitude": -122.288371
          },
          {
            "latitude": 47.609964,
            "longitude": -122.2884861
          },
          {
            "latitude": 47.6099221,
            "longitude": -122.2886299
          },
          {
            "latitude": 47.6099149,
            "longitude": -122.2887984
          },
          {
            "latitude": 47.6097756,
            "longitude": -122.2887908
          },
          {
            "latitude": 47.6097584,
            "longitude": -122.2887903
          },
          {
            "latitude": 47.6097229,
            "longitude": -122.2887998
          },
          {
            "latitude": 47.6093113,
            "longitude": -122.2883831
          },
          {
            "latitude": 47.6092448,
            "longitude": -122.2883318
          },
          {
            "latitude": 47.6090876,
            "longitude": -122.2882897
          },
          {
            "latitude": 47.6089304,
            "longitude": -122.2883318
          },
          {
            "latitude": 47.6088154,
            "longitude": -122.2884469
          },
          {
            "latitude": 47.6087732,
            "longitude": -122.2886041
          },
          {
            "latitude": 47.6087733,
            "longitude": -122.2886076
          },
          {
            "latitude": 47.6087756,
            "longitude": -122.2888214
          },
          {
            "latitude": 47.6087169,
            "longitude": -122.2888056
          },
          {
            "latitude": 47.6086451,
            "longitude": -122.2888139
          },
          {
            "latitude": 47.6085861,
            "longitude": -122.2888278
          },
          {
            "latitude": 47.6081625,
            "longitude": -122.2886886
          },
          {
            "latitude": 47.6080643,
            "longitude": -122.2886728
          },
          {
            "latitude": 47.6079433,
            "longitude": -122.2887052
          },
          {
            "latitude": 47.6079597,
            "longitude": -122.288644
          },
          {
            "latitude": 47.6079589,
            "longitude": -122.2886216
          },
          {
            "latitude": 47.6079297,
            "longitude": -122.2882119
          },
          {
            "latitude": 47.6079744,
            "longitude": -122.2882302
          },
          {
            "latitude": 47.6080939,
            "longitude": -122.2882538
          },
          {
            "latitude": 47.6082511,
            "longitude": -122.2882117
          },
          {
            "latitude": 47.6083661,
            "longitude": -122.2880966
          },
          {
            "latitude": 47.6084083,
            "longitude": -122.2879394
          },
          {
            "latitude": 47.6083667,
            "longitude": -122.2877842
          },
          {
            "latitude": 47.6084242,
            "longitude": -122.2878417
          },
          {
            "latitude": 47.6085814,
            "longitude": -122.2878839
          },
          {
            "latitude": 47.6087386,
            "longitude": -122.2878417
          },
          {
            "latitude": 47.6087946,
            "longitude": -122.2877858
          },
          {
            "latitude": 47.6088063,
            "longitude": -122.2878098
          },
          {
            "latitude": 47.6089214,
            "longitude": -122.2879249
          },
          {
            "latitude": 47.6090786,
            "longitude": -122.287967
          },
          {
            "latitude": 47.6092358,
            "longitude": -122.2879249
          },
          {
            "latitude": 47.6093509,
            "longitude": -122.2878098
          },
          {
            "latitude": 47.6093679,
            "longitude": -122.2877758
          },
          {
            "latitude": 47.6094279,
            "longitude": -122.2876348
          },
          {
            "latitude": 47.6094408,
            "longitude": -122.287666
          },
          {
            "latitude": 47.6095559,
            "longitude": -122.2877811
          },
          {
            "latitude": 47.6097131,
            "longitude": -122.2878232
          },
          {
            "latitude": 47.6098703,
            "longitude": -122.2877811
          },
          {
            "latitude": 47.6099854,
            "longitude": -122.287666
          },
          {
            "latitude": 47.6100275,
            "longitude": -122.2875088
          },
          {
            "latitude": 47.6100269,
            "longitude": -122.2874894
          },
          {
            "latitude": 47.6099905,
            "longitude": -122.286903
          },
          {
            "latitude": 47.609949,
            "longitude": -122.2867653
          },
          {
            "latitude": 47.6099202,
            "longitude": -122.2867366
          },
          {
            "latitude": 47.6100475,
            "longitude": -122.2867025
          },
          {
            "latitude": 47.6101626,
            "longitude": -122.2865874
          },
          {
            "latitude": 47.6101717,
            "longitude": -122.2865705
          },
          {
            "latitude": 47.6102126,
            "longitude": -122.2864884
          },
          {
            "latitude": 47.6102427,
            "longitude": -122.2866007
          },
          {
            "latitude": 47.6103578,
            "longitude": -122.2867158
          },
          {
            "latitude": 47.610515,
            "longitude": -122.2867579
          },
          {
            "latitude": 47.6106722,
            "longitude": -122.2867158
          },
          {
            "latitude": 47.6107417,
            "longitude": -122.2866463
          },
          {
            "latitude": 47.6108076,
            "longitude": -122.2867122
          },
          {
            "latitude": 47.6109648,
            "longitude": -122.2867543
          },
          {
            "latitude": 47.6110524,
            "longitude": -122.2867419
          },
          {
            "latitude": 47.6113251,
            "longitude": -122.2866628
          },
          {
            "latitude": 47.6113947,
            "longitude": -122.2866331
          },
          {
            "latitude": 47.6115098,
            "longitude": -122.2865181
          },
          {
            "latitude": 47.6115519,
            "longitude": -122.2863609
          },
          {
            "latitude": 47.6115448,
            "longitude": -122.2862942
          },
          {
            "latitude": 47.6113922,
            "longitude": -122.2855909
          },
          {
            "latitude": 47.6113572,
            "longitude": -122.2855004
          },
          {
            "latitude": 47.6112716,
            "longitude": -122.2854046
          },
          {
            "latitude": 47.6112478,
            "longitude": -122.285387
          },
          {
            "latitude": 47.6112876,
            "longitude": -122.2852386
          },
          {
            "latitude": 47.6112532,
            "longitude": -122.2850956
          },
          {
            "latitude": 47.6111422,
            "longitude": -122.2848784
          },
          {
            "latitude": 47.6111345,
            "longitude": -122.2848642
          },
          {
            "latitude": 47.6110277,
            "longitude": -122.2847541
          },
          {
            "latitude": 47.6108335,
            "longitude": -122.2846339
          },
          {
            "latitude": 47.6108252,
            "longitude": -122.2846289
          },
          {
            "latitude": 47.6107183,
            "longitude": -122.2846003
          },
          {
            "latitude": 47.6107123,
            "longitude": -122.2845943
          },
          {
            "latitude": 47.6105551,
            "longitude": -122.2845522
          },
          {
            "latitude": 47.6103979,
            "longitude": -122.2845943
          },
          {
            "latitude": 47.6103859,
            "longitude": -122.2846016
          },
          {
            "latitude": 47.610097,
            "longitude": -122.2847861
          },
          {
            "latitude": 47.6100233,
            "longitude": -122.2847644
          },
          {
            "latitude": 47.6095531,
            "longitude": -122.2847417
          },
          {
            "latitude": 47.6095379,
            "longitude": -122.2847414
          },
          {
            "latitude": 47.6093807,
            "longitude": -122.2847835
          },
          {
            "latitude": 47.6093338,
            "longitude": -122.2848305
          },
          {
            "latitude": 47.6093746,
            "longitude": -122.2846255
          },
          {
            "latitude": 47.6093807,
            "longitude": -122.2845641
          },
          {
            "latitude": 47.6093385,
            "longitude": -122.2844069
          },
          {
            "latitude": 47.6092235,
            "longitude": -122.2842918
          },
          {
            "latitude": 47.6091238,
            "longitude": -122.284255
          },
          {
            "latitude": 47.6090847,
            "longitude": -122.2842477
          },
          {
            "latitude": 47.6092315,
            "longitude": -122.2841332
          },
          {
            "latitude": 47.6093103,
            "longitude": -122.2840425
          },
          {
            "latitude": 47.6093524,
            "longitude": -122.2838853
          },
          {
            "latitude": 47.6093103,
            "longitude": -122.2837281
          },
          {
            "latitude": 47.6091952,
            "longitude": -122.283613
          },
          {
            "latitude": 47.609038,
            "longitude": -122.2835709
          },
          {
            "latitude": 47.6090344,
            "longitude": -122.2835709
          },
          {
            "latitude": 47.608736,
            "longitude": -122.2835744
          },
          {
            "latitude": 47.6085825,
            "longitude": -122.2836165
          },
          {
            "latitude": 47.6085737,
            "longitude": -122.2836237
          },
          {
            "latitude": 47.6085387,
            "longitude": -122.2836086
          },
          {
            "latitude": 47.6082998,
            "longitude": -122.2835378
          },
          {
            "latitude": 47.6082116,
            "longitude": -122.2835248
          },
          {
            "latitude": 47.608155,
            "longitude": -122.2835246
          },
          {
            "latitude": 47.6080809,
            "longitude": -122.2834505
          },
          {
            "latitude": 47.6079737,
            "longitude": -122.2834123
          },
          {
            "latitude": 47.6076089,
            "longitude": -122.2833535
          },
          {
            "latitude": 47.6075589,
            "longitude": -122.2833495
          },
          {
            "latitude": 47.6075477,
            "longitude": -122.2833497
          },
          {
            "latitude": 47.6071829,
            "longitude": -122.2833627
          },
          {
            "latitude": 47.6070369,
            "longitude": -122.2834046
          },
          {
            "latitude": 47.6069218,
            "longitude": -122.2835197
          },
          {
            "latitude": 47.6068877,
            "longitude": -122.2836471
          },
          {
            "latitude": 47.6068244,
            "longitude": -122.2836641
          },
          {
            "latitude": 47.6067317,
            "longitude": -122.2835713
          },
          {
            "latitude": 47.6066379,
            "longitude": -122.2835357
          },
          {
            "latitude": 47.6065459,
            "longitude": -122.2835167
          },
          {
            "latitude": 47.6064825,
            "longitude": -122.2835103
          },
          {
            "latitude": 47.6063259,
            "longitude": -122.2835521
          },
          {
            "latitude": 47.6062829,
            "longitude": -122.2835767
          },
          {
            "latitude": 47.6061197,
            "longitude": -122.2835549
          },
          {
            "latitude": 47.6060781,
            "longitude": -122.2835522
          },
          {
            "latitude": 47.6060494,
            "longitude": -122.2835535
          },
          {
            "latitude": 47.6057971,
            "longitude": -122.2835766
          },
          {
            "latitude": 47.6057895,
            "longitude": -122.283569
          },
          {
            "latitude": 47.6057313,
            "longitude": -122.2835428
          },
          {
            "latitude": 47.6054631,
            "longitude": -122.2834539
          },
          {
            "latitude": 47.6054065,
            "longitude": -122.2834408
          },
          {
            "latitude": 47.6051723,
            "longitude": -122.2834089
          },
          {
            "latitude": 47.6051575,
            "longitude": -122.2833971
          },
          {
            "latitude": 47.6050003,
            "longitude": -122.2833549
          },
          {
            "latitude": 47.6049764,
            "longitude": -122.2833613
          },
          {
            "latitude": 47.6049831,
            "longitude": -122.2833163
          },
          {
            "latitude": 47.6049865,
            "longitude": -122.2832701
          },
          {
            "latitude": 47.6049444,
            "longitude": -122.2831129
          },
          {
            "latitude": 47.6048293,
            "longitude": -122.2829978
          },
          {
            "latitude": 47.6046721,
            "longitude": -122.2829557
          },
          {
            "latitude": 47.6045149,
            "longitude": -122.2829978
          },
          {
            "latitude": 47.6043998,
            "longitude": -122.2831129
          },
          {
            "latitude": 47.6043934,
            "longitude": -122.2831245
          },
          {
            "latitude": 47.6040853,
            "longitude": -122.2837147
          },
          {
            "latitude": 47.6038828,
            "longitude": -122.2834352
          },
          {
            "latitude": 47.6037854,
            "longitude": -122.2833474
          },
          {
            "latitude": 47.6036282,
            "longitude": -122.2833053
          },
          {
            "latitude": 47.603471,
            "longitude": -122.2833474
          },
          {
            "latitude": 47.6033559,
            "longitude": -122.2834625
          },
          {
            "latitude": 47.6033138,
            "longitude": -122.2836197
          },
          {
            "latitude": 47.603345,
            "longitude": -122.2837562
          },
          {
            "latitude": 47.6036069,
            "longitude": -122.2842993
          },
          {
            "latitude": 47.603566,
            "longitude": -122.2843402
          },
          {
            "latitude": 47.6035595,
            "longitude": -122.2843521
          },
          {
            "latitude": 47.6034878,
            "longitude": -122.2844896
          },
          {
            "latitude": 47.6034059,
            "longitude": -122.2844676
          },
          {
            "latitude": 47.6032487,
            "longitude": -122.2845098
          },
          {
            "latitude": 47.6032044,
            "longitude": -122.2845407
          },
          {
            "latitude": 47.6031434,
            "longitude": -122.2845917
          },
          {
            "latitude": 47.6030842,
            "longitude": -122.2846572
          },
          {
            "latitude": 47.60306,
            "longitude": -122.2846931
          },
          {
            "latitude": 47.6030484,
            "longitude": -122.2847117
          },
          {
            "latitude": 47.6030312,
            "longitude": -122.2847462
          },
          {
            "latitude": 47.6029944,
            "longitude": -122.2848331
          },
          {
            "latitude": 47.6029695,
            "longitude": -122.2849557
          },
          {
            "latitude": 47.6029873,
            "longitude": -122.285022
          },
          {
            "latitude": 47.6029713,
            "longitude": -122.2850175
          },
          {
            "latitude": 47.6028865,
            "longitude": -122.2850059
          },
          {
            "latitude": 47.6027293,
            "longitude": -122.285048
          },
          {
            "latitude": 47.6026143,
            "longitude": -122.2851631
          },
          {
            "latitude": 47.6025996,
            "longitude": -122.2851917
          },
          {
            "latitude": 47.602598,
            "longitude": -122.2851953
          },
          {
            "latitude": 47.6025388,
            "longitude": -122.2851401
          },
          {
            "latitude": 47.6023816,
            "longitude": -122.285098
          },
          {
            "latitude": 47.6022244,
            "longitude": -122.2851401
          },
          {
            "latitude": 47.6021209,
            "longitude": -122.2852366
          },
          {
            "latitude": 47.6020967,
            "longitude": -122.2852725
          },
          {
            "latitude": 47.6020851,
            "longitude": -122.2852911
          },
          {
            "latitude": 47.602043,
            "longitude": -122.2854483
          },
          {
            "latitude": 47.6020826,
            "longitude": -122.2855961
          },
          {
            "latitude": 47.6020211,
            "longitude": -122.2855797
          },
          {
            "latitude": 47.601998,
            "longitude": -122.2855859
          },
          {
            "latitude": 47.6019563,
            "longitude": -122.2855747
          },
          {
            "latitude": 47.6010205,
            "longitude": -122.2847325
          },
          {
            "latitude": 47.6009674,
            "longitude": -122.2846939
          },
          {
            "latitude": 47.6008102,
            "longitude": -122.2846517
          },
          {
            "latitude": 47.600653,
            "longitude": -122.2846939
          },
          {
            "latitude": 47.6005379,
            "longitude": -122.2848089
          },
          {
            "latitude": 47.6004958,
            "longitude": -122.2849661
          },
          {
            "latitude": 47.6005221,
            "longitude": -122.2850922
          },
          {
            "latitude": 47.6014718,
            "longitude": -122.2872623
          },
          {
            "latitude": 47.6014876,
            "longitude": -122.2872934
          },
          {
            "latitude": 47.6016027,
            "longitude": -122.2874085
          },
          {
            "latitude": 47.6016626,
            "longitude": -122.2874246
          },
          {
            "latitude": 47.601647,
            "longitude": -122.2874828
          },
          {
            "latitude": 47.6016495,
            "longitude": -122.287523
          },
          {
            "latitude": 47.6016698,
            "longitude": -122.2876805
          },
          {
            "latitude": 47.6015739,
            "longitude": -122.2877764
          },
          {
            "latitude": 47.6015318,
            "longitude": -122.2879336
          },
          {
            "latitude": 47.6015322,
            "longitude": -122.2879483
          },
          {
            "latitude": 47.6015571,
            "longitude": -122.2884803
          },
          {
            "latitude": 47.6015586,
            "longitude": -122.2884991
          },
          {
            "latitude": 47.6015816,
            "longitude": -122.2887135
          },
          {
            "latitude": 47.6016136,
            "longitude": -122.2888114
          },
          {
            "latitude": 47.6015985,
            "longitude": -122.2888677
          },
          {
            "latitude": 47.6015985,
            "longitude": -122.2888708
          },
          {
            "latitude": 47.6016007,
            "longitude": -122.2890921
          },
          {
            "latitude": 47.6016232,
            "longitude": -122.2892057
          },
          {
            "latitude": 47.6017024,
            "longitude": -122.2894039
          },
          {
            "latitude": 47.6016657,
            "longitude": -122.2894347
          },
          {
            "latitude": 47.6012726,
            "longitude": -122.2899061
          },
          {
            "latitude": 47.6012257,
            "longitude": -122.2898592
          },
          {
            "latitude": 47.6010685,
            "longitude": -122.289817
          },
          {
            "latitude": 47.6009113,
            "longitude": -122.2898592
          },
          {
            "latitude": 47.6008478,
            "longitude": -122.2899074
          },
          {
            "latitude": 47.6002929,
            "longitude": -122.290454
          },
          {
            "latitude": 47.6002412,
            "longitude": -122.2905208
          },
          {
            "latitude": 47.6002036,
            "longitude": -122.2906612
          },
          {
            "latitude": 47.6001333,
            "longitude": -122.2906801
          },
          {
            "latitude": 47.6000182,
            "longitude": -122.2907951
          },
          {
            "latitude": 47.5999761,
            "longitude": -122.2909523
          },
          {
            "latitude": 47.5999762,
            "longitude": -122.2909605
          },
          {
            "latitude": 47.5999952,
            "longitude": -122.2916903
          },
          {
            "latitude": 47.6000059,
            "longitude": -122.2917639
          },
          {
            "latitude": 47.6000854,
            "longitude": -122.2920588
          },
          {
            "latitude": 47.6000099,
            "longitude": -122.292136
          },
          {
            "latitude": 47.5999678,
            "longitude": -122.2922932
          },
          {
            "latitude": 47.5999791,
            "longitude": -122.2923767
          },
          {
            "latitude": 47.6000699,
            "longitude": -122.2927067
          },
          {
            "latitude": 47.599779,
            "longitude": -122.2928611
          },
          {
            "latitude": 47.5997692,
            "longitude": -122.2928665
          },
          {
            "latitude": 47.5996541,
            "longitude": -122.2929816
          },
          {
            "latitude": 47.5996187,
            "longitude": -122.2931136
          },
          {
            "latitude": 47.5995344,
            "longitude": -122.2931056
          },
          {
            "latitude": 47.5995047,
            "longitude": -122.2931042
          },
          {
            "latitude": 47.5993475,
            "longitude": -122.2931463
          },
          {
            "latitude": 47.5992324,
            "longitude": -122.2932614
          },
          {
            "latitude": 47.5991903,
            "longitude": -122.2934186
          },
          {
            "latitude": 47.5991915,
            "longitude": -122.293446
          },
          {
            "latitude": 47.599255,
            "longitude": -122.2941695
          },
          {
            "latitude": 47.5992959,
            "longitude": -122.2942992
          },
          {
            "latitude": 47.599411,
            "longitude": -122.2944143
          },
          {
            "latitude": 47.5995273,
            "longitude": -122.2944488
          },
          {
            "latitude": 47.599314,
            "longitude": -122.2945448
          },
          {
            "latitude": 47.5992858,
            "longitude": -122.2945592
          },
          {
            "latitude": 47.5992244,
            "longitude": -122.2946055
          },
          {
            "latitude": 47.5988286,
            "longitude": -122.2949883
          },
          {
            "latitude": 47.5988276,
            "longitude": -122.2949896
          },
          {
            "latitude": 47.5987736,
            "longitude": -122.2949751
          },
          {
            "latitude": 47.5986164,
            "longitude": -122.2950172
          },
          {
            "latitude": 47.5985129,
            "longitude": -122.2951138
          },
          {
            "latitude": 47.5984887,
            "longitude": -122.2951497
          },
          {
            "latitude": 47.5984771,
            "longitude": -122.2951682
          }
        ]
      }
    ],
    "publicVisibility": true,
    "enabled": false,
    "manual": false,
    "images": [],
    "rules": [],
    "actions": [],
    "city": "South Seattle",
    "state": "WA",
    "affectedMunicipalities": [],
    "affectedCounties": [],
    "affectedDistricts": []
  }
]
