[
  {
    "id": 903032,
    "startDate": "Sat Feb 13 04:38:00 UTC 2021",
    "etrDate": "Sat Feb 13 22:19:00 UTC 2021",
    "type": "OUTAGE",
    "title": "Outage",
    "numPeople": 38,
    "mapPinUrl": "",
    "status": "",
    "cause": "Car/Pole",
    "identifier": "122757",
    "latitude": 47.4693721572734,
    "longitude": -122.33392220802335,
    "polygons": [
      {
        "points": [
          {
            "latitude": 47.466908,
            "longitude": -122.3340267
          },
          {
            "latitude": 47.4668838,
            "longitude": -122.3340626
          },
          {
            "latitude": 47.4668722,
            "longitude": -122.3340812
          },
          {
            "latitude": 47.4668301,
            "longitude": -122.3342384
          },
          {
            "latitude": 47.4668722,
            "longitude": -122.3343956
          },
          {
            "latitude": 47.4668838,
            "longitude": -122.3344141
          },
          {
            "latitude": 47.466908,
            "longitude": -122.33445
          },
          {
            "latitude": 47.4670115,
            "longitude": -122.3345466
          },
          {
            "latitude": 47.4671687,
            "longitude": -122.3345887
          },
          {
            "latitude": 47.4673259,
            "longitude": -122.3345466
          },
          {
            "latitude": 47.4674293,
            "longitude": -122.33445
          },
          {
            "latitude": 47.4674536,
            "longitude": -122.3344141
          },
          {
            "latitude": 47.4674651,
            "longitude": -122.3343956
          },
          {
            "latitude": 47.4675073,
            "longitude": -122.3342384
          },
          {
            "latitude": 47.4674651,
            "longitude": -122.3340812
          },
          {
            "latitude": 47.4674536,
            "longitude": -122.3340626
          },
          {
            "latitude": 47.4674293,
            "longitude": -122.3340267
          },
          {
            "latitude": 47.4673259,
            "longitude": -122.3339302
          },
          {
            "latitude": 47.4671687,
            "longitude": -122.3338881
          },
          {
            "latitude": 47.4670115,
            "longitude": -122.3339302
          }
        ]
      },
      {
        "points": [
          {
            "latitude": 47.4678638,
            "longitude": -122.3331584
          },
          {
            "latitude": 47.467906,
            "longitude": -122.3333156
          },
          {
            "latitude": 47.4679175,
            "longitude": -122.3333341
          },
          {
            "latitude": 47.4679417,
            "longitude": -122.33337
          },
          {
            "latitude": 47.4680452,
            "longitude": -122.3334665
          },
          {
            "latitude": 47.4682024,
            "longitude": -122.3335087
          },
          {
            "latitude": 47.468225,
            "longitude": -122.3335026
          },
          {
            "latitude": 47.4683409,
            "longitude": -122.3335461
          },
          {
            "latitude": 47.4683008,
            "longitude": -122.3336957
          },
          {
            "latitude": 47.4683218,
            "longitude": -122.3338086
          },
          {
            "latitude": 47.4685895,
            "longitude": -122.3345049
          },
          {
            "latitude": 47.4685887,
            "longitude": -122.3345077
          },
          {
            "latitude": 47.4686309,
            "longitude": -122.3346649
          },
          {
            "latitude": 47.4686425,
            "longitude": -122.3346834
          },
          {
            "latitude": 47.4686667,
            "longitude": -122.3347193
          },
          {
            "latitude": 47.4687702,
            "longitude": -122.3348158
          },
          {
            "latitude": 47.4689274,
            "longitude": -122.334858
          },
          {
            "latitude": 47.4690846,
            "longitude": -122.3348158
          },
          {
            "latitude": 47.4690918,
            "longitude": -122.3348091
          },
          {
            "latitude": 47.4699735,
            "longitude": -122.3347334
          },
          {
            "latitude": 47.4698445,
            "longitude": -122.334768
          },
          {
            "latitude": 47.469741,
            "longitude": -122.3348645
          },
          {
            "latitude": 47.4697168,
            "longitude": -122.3349004
          },
          {
            "latitude": 47.4697052,
            "longitude": -122.3349189
          },
          {
            "latitude": 47.4696631,
            "longitude": -122.3350761
          },
          {
            "latitude": 47.4697052,
            "longitude": -122.3352333
          },
          {
            "latitude": 47.4697168,
            "longitude": -122.3352519
          },
          {
            "latitude": 47.469741,
            "longitude": -122.3352878
          },
          {
            "latitude": 47.4698445,
            "longitude": -122.3353843
          },
          {
            "latitude": 47.4700017,
            "longitude": -122.3354264
          },
          {
            "latitude": 47.4701589,
            "longitude": -122.3353843
          },
          {
            "latitude": 47.4702624,
            "longitude": -122.3352878
          },
          {
            "latitude": 47.4702866,
            "longitude": -122.3352519
          },
          {
            "latitude": 47.4702981,
            "longitude": -122.3352333
          },
          {
            "latitude": 47.4703403,
            "longitude": -122.3350761
          },
          {
            "latitude": 47.4702981,
            "longitude": -122.3349189
          },
          {
            "latitude": 47.4702866,
            "longitude": -122.3349004
          },
          {
            "latitude": 47.4702624,
            "longitude": -122.3348645
          },
          {
            "latitude": 47.4701589,
            "longitude": -122.334768
          },
          {
            "latitude": 47.4700161,
            "longitude": -122.3347297
          },
          {
            "latitude": 47.4703385,
            "longitude": -122.3347021
          },
          {
            "latitude": 47.4704688,
            "longitude": -122.3346611
          },
          {
            "latitude": 47.4705838,
            "longitude": -122.334546
          },
          {
            "latitude": 47.470626,
            "longitude": -122.3343888
          },
          {
            "latitude": 47.4705838,
            "longitude": -122.3342316
          },
          {
            "latitude": 47.4704688,
            "longitude": -122.3341165
          },
          {
            "latitude": 47.4704305,
            "longitude": -122.3340978
          },
          {
            "latitude": 47.4698978,
            "longitude": -122.3338801
          },
          {
            "latitude": 47.4699287,
            "longitude": -122.3338719
          },
          {
            "latitude": 47.4700438,
            "longitude": -122.3337568
          },
          {
            "latitude": 47.4700498,
            "longitude": -122.3337341
          },
          {
            "latitude": 47.470088,
            "longitude": -122.3337697
          },
          {
            "latitude": 47.4702452,
            "longitude": -122.3338118
          },
          {
            "latitude": 47.4704024,
            "longitude": -122.3337697
          },
          {
            "latitude": 47.4705059,
            "longitude": -122.3336732
          },
          {
            "latitude": 47.4705301,
            "longitude": -122.3336373
          },
          {
            "latitude": 47.4705417,
            "longitude": -122.3336187
          },
          {
            "latitude": 47.4705838,
            "longitude": -122.3334615
          },
          {
            "latitude": 47.4705417,
            "longitude": -122.3333043
          },
          {
            "latitude": 47.4705301,
            "longitude": -122.3332858
          },
          {
            "latitude": 47.4705059,
            "longitude": -122.3332499
          },
          {
            "latitude": 47.4704024,
            "longitude": -122.3331534
          },
          {
            "latitude": 47.4702452,
            "longitude": -122.3331112
          },
          {
            "latitude": 47.4702183,
            "longitude": -122.3331185
          },
          {
            "latitude": 47.4702141,
            "longitude": -122.3331123
          },
          {
            "latitude": 47.4701106,
            "longitude": -122.3330157
          },
          {
            "latitude": 47.4699534,
            "longitude": -122.3329736
          },
          {
            "latitude": 47.4697962,
            "longitude": -122.3330157
          },
          {
            "latitude": 47.4696927,
            "longitude": -122.3331123
          },
          {
            "latitude": 47.4696685,
            "longitude": -122.3331482
          },
          {
            "latitude": 47.4696569,
            "longitude": -122.3331667
          },
          {
            "latitude": 47.4696519,
            "longitude": -122.3331857
          },
          {
            "latitude": 47.4695957,
            "longitude": -122.3331571
          },
          {
            "latitude": 47.4694708,
            "longitude": -122.3331233
          },
          {
            "latitude": 47.4693035,
            "longitude": -122.3331138
          },
          {
            "latitude": 47.4693031,
            "longitude": -122.3331138
          },
          {
            "latitude": 47.4692824,
            "longitude": -122.3330532
          },
          {
            "latitude": 47.4692571,
            "longitude": -122.3329975
          },
          {
            "latitude": 47.469142,
            "longitude": -122.3328824
          },
          {
            "latitude": 47.4689848,
            "longitude": -122.3328403
          },
          {
            "latitude": 47.4689833,
            "longitude": -122.3328403
          },
          {
            "latitude": 47.4683341,
            "longitude": -122.3328433
          },
          {
            "latitude": 47.4682024,
            "longitude": -122.3328081
          },
          {
            "latitude": 47.4680452,
            "longitude": -122.3328502
          },
          {
            "latitude": 47.4679417,
            "longitude": -122.3329467
          },
          {
            "latitude": 47.4679175,
            "longitude": -122.3329826
          },
          {
            "latitude": 47.467906,
            "longitude": -122.3330012
          }
        ]
      }
    ],
    "publicVisibility": true,
    "enabled": false,
    "manual": false,
    "images": [],
    "rules": [],
    "actions": [],
    "city": "South Seattle",
    "state": "WA",
    "affectedMunicipalities": [],
    "affectedCounties": [],
    "affectedDistricts": []
  },
  {
    "id": 903077,
    "startDate": "Sat Feb 13 16:12:00 UTC 2021",
    "etrDate": "Sat Feb 13 21:00:00 UTC 2021",
    "type": "OUTAGE",
    "title": "Outage",
    "numPeople": 1,
    "mapPinUrl": "",
    "status": "Dispatched",
    "cause": "Investigating",
    "identifier": "122761",
    "latitude": 47.76431337842213,
    "longitude": -122.28787608128944,
    "polygons": [
      {
        "points": [
          {
            "latitude": 47.764055,
            "longitude": -122.2876702
          },
          {
            "latitude": 47.7640308,
            "longitude": -122.2877061
          },
          {
            "latitude": 47.7640192,
            "longitude": -122.2877247
          },
          {
            "latitude": 47.763977,
            "longitude": -122.2878819
          },
          {
            "latitude": 47.7640192,
            "longitude": -122.2880391
          },
          {
            "latitude": 47.7640308,
            "longitude": -122.2880576
          },
          {
            "latitude": 47.764055,
            "longitude": -122.2880935
          },
          {
            "latitude": 47.7641584,
            "longitude": -122.2881901
          },
          {
            "latitude": 47.7643156,
            "longitude": -122.2882322
          },
          {
            "latitude": 47.7644728,
            "longitude": -122.2881901
          },
          {
            "latitude": 47.7645763,
            "longitude": -122.2880935
          },
          {
            "latitude": 47.7646005,
            "longitude": -122.2880576
          },
          {
            "latitude": 47.7646121,
            "longitude": -122.2880391
          },
          {
            "latitude": 47.7646542,
            "longitude": -122.2878819
          },
          {
            "latitude": 47.7646121,
            "longitude": -122.2877247
          },
          {
            "latitude": 47.7646005,
            "longitude": -122.2877061
          },
          {
            "latitude": 47.7645763,
            "longitude": -122.2876702
          },
          {
            "latitude": 47.7644728,
            "longitude": -122.2875737
          },
          {
            "latitude": 47.7643156,
            "longitude": -122.2875316
          },
          {
            "latitude": 47.7641584,
            "longitude": -122.2875737
          }
        ]
      }
    ],
    "publicVisibility": true,
    "enabled": false,
    "manual": false,
    "images": [],
    "rules": [],
    "actions": [],
    "city": "North Seattle",
    "state": "WA",
    "affectedMunicipalities": [],
    "affectedCounties": [],
    "affectedDistricts": []
  },
  {
    "id": 903084,
    "startDate": "Sat Feb 13 13:51:00 UTC 2021",
    "etrDate": "Sun Feb 14 10:00:00 UTC 2021",
    "type": "OUTAGE",
    "title": "Outage",
    "numPeople": 2,
    "mapPinUrl": "",
    "status": "Dispatched",
    "cause": "Equip_Fail",
    "identifier": "122762",
    "latitude": 47.62680106327879,
    "longitude": -122.31537345093886,
    "polygons": [
      {
        "points": [
          {
            "latitude": 47.6270844,
            "longitude": -122.3156432
          },
          {
            "latitude": 47.6271086,
            "longitude": -122.3156073
          },
          {
            "latitude": 47.6271202,
            "longitude": -122.3155888
          },
          {
            "latitude": 47.6271623,
            "longitude": -122.3154316
          },
          {
            "latitude": 47.6271202,
            "longitude": -122.3152744
          },
          {
            "latitude": 47.6271086,
            "longitude": -122.3152558
          },
          {
            "latitude": 47.6270844,
            "longitude": -122.3152199
          },
          {
            "latitude": 47.6269809,
            "longitude": -122.3151234
          },
          {
            "latitude": 47.6268237,
            "longitude": -122.3150813
          },
          {
            "latitude": 47.6266665,
            "longitude": -122.3151234
          },
          {
            "latitude": 47.626563,
            "longitude": -122.3152199
          },
          {
            "latitude": 47.6265388,
            "longitude": -122.3152558
          },
          {
            "latitude": 47.6265272,
            "longitude": -122.3152744
          },
          {
            "latitude": 47.6264851,
            "longitude": -122.3154316
          },
          {
            "latitude": 47.6265272,
            "longitude": -122.3155888
          },
          {
            "latitude": 47.6265388,
            "longitude": -122.3156073
          },
          {
            "latitude": 47.626563,
            "longitude": -122.3156432
          },
          {
            "latitude": 47.6266665,
            "longitude": -122.3157398
          },
          {
            "latitude": 47.6268237,
            "longitude": -122.3157819
          },
          {
            "latitude": 47.6269809,
            "longitude": -122.3157398
          }
        ]
      }
    ],
    "publicVisibility": true,
    "enabled": false,
    "manual": false,
    "images": [],
    "rules": [],
    "actions": [],
    "city": "North Seattle",
    "state": "WA",
    "affectedMunicipalities": [],
    "affectedCounties": [],
    "affectedDistricts": []
  }
]
